simple_jwt/__about__.py
simple_jwt/__init__.py
simple_jwt/cli.py
simple_jwt/jwt.py
simple_jwt_decode-0.10.0.dist-info/METADATA
simple_jwt_decode-0.10.0.dist-info/WHEEL
simple_jwt_decode-0.10.0.dist-info/entry_points.txt
simple_jwt_decode-0.10.0.dist-info/licenses/LICENSE.txt
simple_jwt_decode-0.10.0.dist-info/RECORD
