Metadata-Version: 2.4
Name: simple-jwt-decode
Version: 0.10.0
Summary: Simple Python Package for decoding JWT claims and checking if its expired. No verification of signatures.
Project-URL: Documentation, https://github.com/u-clarkdeveloper/simple-jwt#readme
Project-URL: Issues, https://github.com/u-clarkdeveloper/simple-jwt/issues
Project-URL: Source, https://github.com/u-clarkdeveloper/simple-jwt
Author-email: Jesse Clark <jesse@clarkdeveloper.com>
License-Expression: MIT
License-File: LICENSE.txt
Classifier: Development Status :: 4 - Beta
Classifier: Programming Language :: Python
Classifier: Programming Language :: Python :: 3.7
Classifier: Programming Language :: Python :: 3.8
Classifier: Programming Language :: Python :: 3.9
Classifier: Programming Language :: Python :: 3.10
Classifier: Programming Language :: Python :: 3.11
Classifier: Programming Language :: Python :: Implementation :: CPython
Classifier: Programming Language :: Python :: Implementation :: PyPy
Requires-Python: >=3.7
